AUTHORS
LICENSE
MANIFEST.in
README.md
setup.py
hdfs/__init__.py
hdfs/__main__.py
hdfs/client.py
hdfs/config.py
hdfs/util.py
hdfs/ext/__init__.py
hdfs/ext/dataframe.py
hdfs/ext/kerberos.py
hdfs/ext/avro/__init__.py
hdfs/ext/avro/__main__.py
tbds_hdfs.egg-info/PKG-INFO
tbds_hdfs.egg-info/SOURCES.txt
tbds_hdfs.egg-info/dependency_links.txt
tbds_hdfs.egg-info/entry_points.txt
tbds_hdfs.egg-info/requires.txt
tbds_hdfs.egg-info/top_level.txt
test/test_client.py
test/test_config.py
test/test_examples.py
test/test_ext_avro.py
test/test_ext_dataframe.py
test/test_ext_kerberos.py
test/test_main.py
test/test_util.py